markdown_data_tables/__init__.py
markdown_data_tables-1.0.0.dist-info/LICENSE
markdown_data_tables-1.0.0.dist-info/METADATA
markdown_data_tables-1.0.0.dist-info/WHEEL
markdown_data_tables-1.0.0.dist-info/RECORD
